yOpenApi/__init__.py
yOpenApi-0.0.1.dist-info/METADATA
yOpenApi-0.0.1.dist-info/WHEEL
yOpenApi-0.0.1.dist-info/top_level.txt
yOpenApi-0.0.1.dist-info/RECORD
