Metadata-Version: 2.1
Name: yOpenApi
Version: 0.0.1
Summary: OpenApi for yModel and ySanic
Home-page: https://github.com/Garito/yOpenApi
Author: Garito
Author-email: garito@gmail.com
License: GPLv3+
Keywords: openapi marshmallow ySanic
Platform: UNKNOWN
Classifier: Development Status :: 4 - Beta
Classifier: Environment :: Plugins
Classifier: Intended Audience :: Developers
Classifier: License :: OSI Approved :: GNU General Public License v3 or later (GPLv3+)
Classifier: Programming Language :: Python :: 3
Classifier: Topic :: Database
Requires-Dist: yModel
Requires-Dist: ySanic
